Titleman/__init__.py
Titleman/icon.ico
titleman-0.1.dist-info/WHEEL
titleman-0.1.dist-info/METADATA
titleman-0.1.dist-info/RECORD
