Metadata-Version: 2.1
Name: Titleman
Version: 0.1
Summary: Titleman customizeds the titlebar of your app.
Author-email: Johnny <johndrostan@outlook.com>
Requires-Python: >=3.5
Classifier: License :: OSI Approved :: MIT License
